topsis_mohit_102397005/__init__.py
topsis_mohit_102397005/topsis_102397005.py
topsis_mohit_102397005-1.0.22.dist-info/LICENSE
topsis_mohit_102397005-1.0.22.dist-info/METADATA
topsis_mohit_102397005-1.0.22.dist-info/WHEEL
topsis_mohit_102397005-1.0.22.dist-info/top_level.txt
topsis_mohit_102397005-1.0.22.dist-info/RECORD
