Metadata-Version: 2.2
Name: topsis_mohit_102397005
Version: 1.0.22
Summary: Topsis technique for MCDM
Author: Mohit Bansal
Author-email: mohitbansal0031@gmail.com
Keywords: python,topsis,mcdm,decision making
Classifier: Development Status :: 1 - Planning
Classifier: Intended Audience :: Education
Classifier: Programming Language :: Python :: 3
Classifier: Operating System :: Unix
Classifier: Operating System :: MacOS :: MacOS X
Classifier: Operating System :: Microsoft :: Windows
License-File: LICENSE
Requires-Dist: pandas
Requires-Dist: numpy
Dynamic: author
Dynamic: author-email
Dynamic: classifier
Dynamic: description
Dynamic: description-content-type
Dynamic: keywords
Dynamic: requires-dist
Dynamic: summary
